cybersharing/api.py
cybersharing/config.py
cybersharing/encryption.py
cybersharing/main.py
cybersharing-1.0.1.dist-info/LICENSE
cybersharing-1.0.1.dist-info/METADATA
cybersharing-1.0.1.dist-info/WHEEL
cybersharing-1.0.1.dist-info/entry_points.txt
cybersharing-1.0.1.dist-info/top_level.txt
cybersharing-1.0.1.dist-info/RECORD
