Metadata-Version: 2.2
Name: cybersharing
Version: 1.0.1
Summary: The official Cybersharing CLI
Author-email: Et3rnos <et3rnos@gmail.com>
Project-URL: Homepage, https://github.com/Et3rnos/cybersharing-cli
Project-URL: Issues, https://github.com/Et3rnos/cybersharing-cli/issues
License-File: LICENSE
Requires-Dist: pycryptodome
Requires-Dist: requests
Requires-Dist: requests_toolbelt
Requires-Dist: typer
